pykappa/__init__.py
pykappa/algebra.py
pykappa/grammar.py
pykappa/kappa.lark
pykappa/mixture.py
pykappa/pattern.py
pykappa/rule.py
pykappa/system.py
pykappa/utils.py
pykappa-0.1.6.dist-info/METADATA
pykappa-0.1.6.dist-info/WHEEL
pykappa-0.1.6.dist-info/top_level.txt
pykappa-0.1.6.dist-info/RECORD
