Metadata-Version: 2.4
Name: pykappa
Version: 0.1.6
Summary: Work with Kappa rule-based models in Python
Project-URL: Homepage, https://pykappa.org
Project-URL: Documentation, https://pykappa.org/api/index.html
Project-URL: Repository, https://github.com/berkalpay/pykappa
Project-URL: Issues, https://github.com/berkalpay/pykappa/issues
Requires-Python: >=3.12
Requires-Dist: lark>=1.2.2
Requires-Dist: pandas>=2.0.0
Requires-Dist: matplotlib>=3.10.3
